uw_graphene/__init__.py
uw_graphene/apps.py
uw_graphene/connections.py
uw_graphene/decorators.py
uw_graphene/errors.py
uw_graphene/mutations.py
uw_graphene/utils.py
django_uw_graphene-0.3.5.dist-info/LICENSE
django_uw_graphene-0.3.5.dist-info/METADATA
django_uw_graphene-0.3.5.dist-info/WHEEL
django_uw_graphene-0.3.5.dist-info/top_level.txt
django_uw_graphene-0.3.5.dist-info/RECORD
