Metadata-Version: 2.1
Name: django-uw-graphene
Version: 0.3.5
Summary: A Django app that extends the graphene interface and helpers
Home-page: https://gitlab.com/pmcoelho/django_uw_graphene
Author: Pedro Maia Coelho
Author-email: pmcoelho@protonmail.com
License: MIT
Platform: UNKNOWN
Classifier: Environment :: Web Environment
Classifier: Framework :: Django
Classifier: Intended Audience :: Developers
Classifier: Programming Language :: Python :: 3
License-File: LICENSE
Requires-Dist: graphene-django (>="2.10.0")
Requires-Dist: Django (>="2.2")
